{
    "Component 0": {
        "ps-t0": [
            "12407ce2-vs=780dc881dc93b724-ps=a47d5181da378692",
            "b4855e43-vs=e3466871196b60b5-ps=d7b6fac6153a2e8e",
            "1fe7c3f1-vs=349759256e847cbf-ps=fa61fc7ad47dc197"
        ],
        "ps-t1": [
            "1091025c-vs=780dc881dc93b724-ps=a47d5181da378692",
            "a1c0d97c-vs=e3466871196b60b5-ps=d7b6fac6153a2e8e"
        ],
        "ps-t2": [
            "99d33a32-vs=780dc881dc93b724-ps=a47d5181da378692"
        ],
        "ps-t5": [
            "0d4205e6-vs=dc03adeeb8656d82-ps=8a6573a48bdc377c"
        ],
        "ps-t6": [
            "8a0e76fc-vs=e3466871196b60b5-ps=f437f05d2d071128",
            "c02e94a7-vs=dc03adeeb8656d82-ps=8a6573a48bdc377c"
        ],
        "ps-t7": [
            "fb01fc68-vs=e3466871196b60b5-ps=f437f05d2d071128",
            "8a0e76fc-vs=dc03adeeb8656d82-ps=8a6573a48bdc377c"
        ],
        "ps-t8": [
            "fb01fc68-vs=dc03adeeb8656d82-ps=8a6573a48bdc377c"
        ]
    },
    "Component 1": {
        "ps-t0": [
            "e17e9a42-vs=fa54394b167d1da8-ps=6f0ca6af85ca78b1",
            "8383cbbf-vs=1731fc2a31a96f7b-ps=ec0b7614b2277f51",
            "1fe7c3f1-vs=e5d20932f1c2194b-ps=fa61fc7ad47dc197"
        ],
        "ps-t1": [
            "7931ea8a-vs=fa54394b167d1da8-ps=6f0ca6af85ca78b1"
        ],
        "ps-t2": [
            "99d33a32-vs=1731fc2a31a96f7b-ps=ec0b7614b2277f51"
        ],
        "ps-t5": [
            "0d4205e6-vs=f6acb88fa931caa2-ps=fdccdc1f2c056cc9"
        ],
        "ps-t6": [
            "8a0e76fc-vs=1731fc2a31a96f7b-ps=ec0b7614b2277f51",
            "c02e94a7-vs=f6acb88fa931caa2-ps=fdccdc1f2c056cc9"
        ],
        "ps-t7": [
            "fb01fc68-vs=1731fc2a31a96f7b-ps=ec0b7614b2277f51",
            "8a0e76fc-vs=f6acb88fa931caa2-ps=fdccdc1f2c056cc9"
        ],
        "ps-t8": [
            "fb01fc68-vs=f6acb88fa931caa2-ps=fdccdc1f2c056cc9"
        ]
    },
    "Component 2": {
        "ps-t0": [
            "454843d1-vs=b25e3a017af68e0d-ps=fa53459ba7257a65",
            "43fd9661-vs=a28d642f3a45ed22-ps=0ffc0c44c8b14b90"
        ],
        "ps-t1": [
            "21993deb-vs=b25e3a017af68e0d-ps=fa53459ba7257a65"
        ],
        "ps-t2": [
            "65af60de-vs=b25e3a017af68e0d-ps=fa53459ba7257a65"
        ],
        "ps-t5": [
            "0d4205e6-vs=e664fc492bc77b44-ps=fdccdc1f2c056cc9"
        ],
        "ps-t6": [
            "8a0e76fc-vs=b25e3a017af68e0d-ps=fa53459ba7257a65",
            "c02e94a7-vs=e664fc492bc77b44-ps=fdccdc1f2c056cc9"
        ],
        "ps-t7": [
            "fb01fc68-vs=b25e3a017af68e0d-ps=fa53459ba7257a65",
            "8a0e76fc-vs=e664fc492bc77b44-ps=fdccdc1f2c056cc9"
        ],
        "ps-t8": [
            "fb01fc68-vs=e664fc492bc77b44-ps=fdccdc1f2c056cc9"
        ]
    },
    "Component 3": {
        "ps-t0": [
            "13bc29e0-vs=0f9ac165d962f701-ps=047c8cb937712368",
            "917263d5-vs=53979d81d9b74f86-ps=0ffc0c44c8b14b90"
        ],
        "ps-t1": [
            "db7ba06b-vs=0f9ac165d962f701-ps=047c8cb937712368"
        ],
        "ps-t5": [
            "0d4205e6-vs=0afa0bf80b5abf94-ps=8a6573a48bdc377c"
        ],
        "ps-t6": [
            "8a0e76fc-vs=0f9ac165d962f701-ps=047c8cb937712368",
            "c02e94a7-vs=0afa0bf80b5abf94-ps=8a6573a48bdc377c"
        ],
        "ps-t7": [
            "fb01fc68-vs=0f9ac165d962f701-ps=047c8cb937712368",
            "8a0e76fc-vs=0afa0bf80b5abf94-ps=8a6573a48bdc377c"
        ],
        "ps-t8": [
            "fb01fc68-vs=0afa0bf80b5abf94-ps=8a6573a48bdc377c"
        ]
    },
    "Component 4": {
        "ps-t0": [
            "8383cbbf-vs=a6826abe5ebb80c9-ps=3430ab7d5cdef57a"
        ],
        "ps-t1": [
            "8383cbbf-vs=84a0ae28d0ade17d-ps=71cd10711a2fe3c2"
        ],
        "ps-t2": [
            "56343b28-vs=84a0ae28d0ade17d-ps=71cd10711a2fe3c2",
            "99d33a32-vs=a6826abe5ebb80c9-ps=3430ab7d5cdef57a"
        ],
        "ps-t5": [
            "0d4205e6-vs=a6826abe5ebb80c9-ps=3430ab7d5cdef57a"
        ],
        "ps-t6": [
            "8a0e76fc-vs=a6826abe5ebb80c9-ps=3430ab7d5cdef57a"
        ],
        "ps-t7": [
            "fb01fc68-vs=a6826abe5ebb80c9-ps=3430ab7d5cdef57a"
        ]
    },
    "Component 5": {
        "ps-t0": [
            "3cd03f60-vs=897e3b254e151f78-ps=2ece26b5ee2f7b83"
        ],
        "ps-t5": [
            "0d4205e6-vs=897e3b254e151f78-ps=2ece26b5ee2f7b83"
        ],
        "ps-t6": [
            "c02e94a7-vs=897e3b254e151f78-ps=2ece26b5ee2f7b83"
        ],
        "ps-t7": [
            "8a0e76fc-vs=897e3b254e151f78-ps=2ece26b5ee2f7b83"
        ],
        "ps-t8": [
            "fb01fc68-vs=897e3b254e151f78-ps=2ece26b5ee2f7b83"
        ]
    }
}